pytest_honors/__init__.py
pytest_honors/constraints/__init__.py
pytest_honors/constraints/iso27001.py
pytest_honors-0.1.4.dist-info/LICENSE
pytest_honors-0.1.4.dist-info/METADATA
pytest_honors-0.1.4.dist-info/WHEEL
pytest_honors-0.1.4.dist-info/entry_points.txt
pytest_honors-0.1.4.dist-info/top_level.txt
pytest_honors-0.1.4.dist-info/RECORD
