Metadata-Version: 2.1
Name: pytest-honors
Version: 0.1.4
Summary: Enforce coverage and report on tests that honor constraints
Home-page: https://github.com/aminohealth/pytest-honors
Author: Amino, Inc
Author-email: foss@amino.com
Maintainer: Amino, Inc
Maintainer-email: foss@amino.com
License: MIT
Project-URL: Documentation, https://pytest-honors.readthedocs.io/en/latest/
Platform: UNKNOWN
Classifier: Development Status :: 4 - Beta
Classifier: Framework :: Pytest
Classifier: Intended Audience :: Developers
Classifier: Topic :: Software Development :: Testing
Classifier: Programming Language :: Python
Classifier: Programming Language :: Python :: 3
Classifier: Programming Language :: Python :: 3.6
Classifier: Programming Language :: Python :: 3.7
Classifier: Programming Language :: Python :: Implementation :: CPython
Classifier: Programming Language :: Python :: Implementation :: PyPy
Classifier: Operating System :: OS Independent
Classifier: License :: OSI Approved :: MIT License
Requires-Python: >=3, !=3.0.*, !=3.1.*, !=3.2.*, !=3.3.*
Requires-Dist: pytest (>=3.5.0)
